{
  "name": "69b6c03c-7b20-4bf0-8319-2096243f3b24",
  "tags": [ "#Live_Order_Bot", "#FAQ_Flow", "#PINWheel_FAQ-alcohol", "#Happy_Path" ],
  "displayName": "PINWheel_FAQ-alcohol_1",
  "testCaseConversationTurns": [ {
    "userInput": {
      "isWebhookEnabled": true,
      "input": {
        "languageCode": "en",
        "event": {
          "event": "WELCOME"
        }
      }
    },
    "virtualAgentOutput": {
      "sessionParameters": {
        "pcAddressChanged": "false",
        "pcContainsAlcohol": "false",
        "pcCourierPrestartOneTracking": "false",
        "pcCourierPrestartTwoTracking": "false",
        "pcDeliveryStatus": "default",
        "pcInteractionType": "default",
        "pcIsVirtualRestaurant": "false",
        "pcMiscPaymentAbuseBlock": "false",
        "pcStoreAddress": "default",
        "pcStorePhoneNumber": "default"
      },
      "differences": [ {
        "type": "PAGE",
        "description": "Page mismatch:\nExpected: \nActual:   Main_Menu_Page",
        "assertionType": "EQUAL",
        "expectedValue": "",
        "actualValue": "Main_Menu_Page"
      }, {
        "type": "UTTERANCE",
        "description": "Agent response mismatch",
        "warning": true,
        "assertionType": "EQUAL",
        "expectedValue": "",
        "actualValue": "\u003cspeak\u003eIn a few words, how can I help you with your current order. You can say things like, the order was already picked up by someone else, ore, problem with customers address.\u003c/speak\u003e"
      } ],
      "currentPage": {
        "name": "Main_Menu_Page",
        "flow": "Default Start Flow"
      },
      "textResponses": [ {
        "text": [ "\u003cspeak\u003eIn a few words, how can I help you with your current order. You can say things like, the order was already picked up by someone else, ore, problem with customers address.\u003c/speak\u003e" ]
      } ],
      "currentFlow": {
        "name": "Default Start Flow"
      },
      "actions": [ {
        "agentUtterance": {
          "text": "\u003cspeak\u003eIn a few words, how can I help you with your current order. You can say things like, the order was already picked up by someone else, ore, problem with customers address.\u003c/speak\u003e"
        }
      } ]
    }
  }, {
    "userInput": {
      "injectedParameters": {
        "pcContainsAlcohol": true,
        "pcDeliveryStatus": "arrived_dropoff_2"
      },
      "isWebhookEnabled": true,
      "input": {
        "text": {
          "text": "i waited a long time"
        },
        "languageCode": "en"
      }
    },
    "virtualAgentOutput": {
      "sessionParameters": {
        "intentName": "LongWait_Vague",
        "isRepeat": "no",
        "pcAddressChanged": "false",
        "pcContainsAlcohol": true,
        "pcCourierPrestartOneTracking": "false",
        "pcCourierPrestartTwoTracking": "false",
        "pcDeliveryStatus": "arrived_dropoff_2",
        "pcInteractionType": "default",
        "pcIsVirtualRestaurant": "false",
        "pcMiscPaymentAbuseBlock": "false",
        "pcStoreAddress": "default",
        "pcStorePhoneNumber": "default"
      },
      "differences": [ {
        "type": "PAGE",
        "description": "Page mismatch:\nExpected: \nActual:   LongWait_Vague_Confirmation",
        "assertionType": "EQUAL",
        "expectedValue": "",
        "actualValue": "LongWait_Vague_Confirmation"
      }, {
        "type": "INTENT",
        "description": "Intent mismatch:\nExpected: \nActual:   LongWait_Vague",
        "assertionType": "EQUAL",
        "expectedValue": "",
        "actualValue": "LongWait_Vague"
      }, {
        "type": "UTTERANCE",
        "description": "Agent response mismatch",
        "warning": true,
        "assertionType": "EQUAL",
        "expectedValue": "",
        "actualValue": "\u003cspeak\u003eI think you're calling about a long wait time, is that correct?\u003c/speak\u003e"
      } ],
      "triggeredIntent": {
        "name": "LongWait_Vague"
      },
      "currentPage": {
        "name": "LongWait_Vague_Confirmation",
        "flow": "Orange Flow"
      },
      "textResponses": [ {
        "text": [ "\u003cspeak\u003eI think you're calling about a long wait time, is that correct?\u003c/speak\u003e" ]
      } ],
      "currentFlow": {
        "name": "Orange Flow"
      },
      "actions": [ {
        "userUtterance": {
          "text": "i waited a long time"
        }
      }, {
        "agentUtterance": {
          "text": "\u003cspeak\u003eI think you're calling about a long wait time, is that correct?\u003c/speak\u003e"
        }
      } ]
    }
  }, {
    "userInput": {
      "isWebhookEnabled": true,
      "input": {
        "text": {
          "text": "yes"
        },
        "languageCode": "en"
      }
    },
    "virtualAgentOutput": {
      "sessionParameters": {
        "dfLastCallerIntent": "LongWait_Vague",
        "intentName": "PINWheel_FAQ-alcohol",
        "isRepeat": "no",
        "pcAddressChanged": "false",
        "pcContainsAlcohol": true,
        "pcCourierPrestartOneTracking": "false",
        "pcCourierPrestartTwoTracking": "false",
        "pcDeliveryStatus": "arrived_dropoff_2",
        "pcInteractionType": "default",
        "pcIsVirtualRestaurant": "false",
        "pcMiscPaymentAbuseBlock": "false",
        "pcStoreAddress": "default",
        "pcStorePhoneNumber": "default"
      },
      "differences": [ {
        "type": "PAGE",
        "description": "Page mismatch:\nExpected: \nActual:   PINWheel_FAQ-alcohol_Response",
        "assertionType": "EQUAL",
        "expectedValue": "",
        "actualValue": "PINWheel_FAQ-alcohol_Response"
      }, {
        "type": "INTENT",
        "description": "Intent mismatch:\nExpected: \nActual:   Confirmation.Yes",
        "assertionType": "EQUAL",
        "expectedValue": "",
        "actualValue": "Confirmation.Yes"
      }, {
        "type": "UTTERANCE",
        "description": "Agent response mismatch",
        "warning": true,
        "assertionType": "EQUAL",
        "expectedValue": "",
        "actualValue": "\u003cspeak\u003eI'm sorry to hear that you're having trouble reaching the customer. Since you are already at the drop off location, you can start the timer by calling, or texting the customer. When the timer expires, you'll be paid for the delivery. You'll also need to return to the store to return the alcohol. Do not leave the alcohol at the door. Don't worry -- you'll be paid for the return trip as well.\u003cbreak time=\"750ms\"/\u003e\u003c/speak\u003e\u003cspeak\u003eTo listen to this message again, just say, repeat it. \u003cbreak time=\"700ms\"/\u003e Is there anything else I can help you with today?\u003c/speak\u003e"
      } ],
      "triggeredIntent": {
        "name": "Confirmation.Yes"
      },
      "currentPage": {
        "name": "PINWheel_FAQ-alcohol_Response",
        "flow": "FAQ Flow"
      },
      "textResponses": [ {
        "text": [ "\u003cspeak\u003eI'm sorry to hear that you're having trouble reaching the customer. Since you are already at the drop off location, you can start the timer by calling, or texting the customer. When the timer expires, you'll be paid for the delivery. You'll also need to return to the store to return the alcohol. Do not leave the alcohol at the door. Don't worry -- you'll be paid for the return trip as well.\u003cbreak time=\"750ms\"/\u003e\u003c/speak\u003e" ]
      }, {
        "text": [ "\u003cspeak\u003eTo listen to this message again, just say, repeat it. \u003cbreak time=\"700ms\"/\u003e Is there anything else I can help you with today?\u003c/speak\u003e" ]
      } ],
      "currentFlow": {
        "name": "FAQ Flow"
      },
      "actions": [ {
        "userUtterance": {
          "text": "yes"
        }
      }, {
        "agentUtterance": {
          "text": "\u003cspeak\u003eI'm sorry to hear that you're having trouble reaching the customer. Since you are already at the drop off location, you can start the timer by calling, or texting the customer. When the timer expires, you'll be paid for the delivery. You'll also need to return to the store to return the alcohol. Do not leave the alcohol at the door. Don't worry -- you'll be paid for the return trip as well.\u003cbreak time=\"750ms\"/\u003e\u003c/speak\u003e\n\u003cspeak\u003eTo listen to this message again, just say, repeat it. \u003cbreak time=\"700ms\"/\u003e Is there anything else I can help you with today?\u003c/speak\u003e"
        }
      } ]
    }
  }, {
    "userInput": {
      "isWebhookEnabled": true,
      "input": {
        "text": {
          "text": "no"
        },
        "languageCode": "en"
      }
    },
    "virtualAgentOutput": {
      "sessionParameters": {
        "dfLastCallerIntent": "LongWait_Vague",
        "isRepeat": "no",
        "pcAddressChanged": "false",
        "pcContainsAlcohol": true,
        "pcCourierPrestartOneTracking": "false",
        "pcCourierPrestartTwoTracking": "false",
        "pcDeliveryStatus": "arrived_dropoff_2",
        "pcInteractionType": "default",
        "pcIsVirtualRestaurant": "false",
        "pcMiscPaymentAbuseBlock": "false",
        "pcStoreAddress": "default",
        "pcStorePhoneNumber": "default",
        "zIntent": "ZHangup"
      },
      "differences": [ {
        "type": "PAGE",
        "description": "Page mismatch:\nExpected: \nActual:   End Session",
        "assertionType": "EQUAL",
        "expectedValue": "",
        "actualValue": "End Session"
      }, {
        "type": "INTENT",
        "description": "Intent mismatch:\nExpected: \nActual:   Confirmation.No",
        "assertionType": "EQUAL",
        "expectedValue": "",
        "actualValue": "Confirmation.No"
      }, {
        "type": "UTTERANCE",
        "description": "Agent response mismatch",
        "warning": true,
        "assertionType": "EQUAL",
        "expectedValue": "",
        "actualValue": "\u003cspeak\u003eThank you for contacting Uber Phone Support.\u003c/speak\u003e\u003cspeak\u003e\u003cbreak time=\"10ms\"/\u003e\u003c/speak\u003e"
      } ],
      "triggeredIntent": {
        "name": "Confirmation.No"
      },
      "currentPage": {
        "name": "End Session",
        "flow": "ZExit"
      },
      "textResponses": [ {
        "text": [ "\u003cspeak\u003eThank you for contacting Uber Phone Support.\u003c/speak\u003e" ]
      }, {
        "text": [ "\u003cspeak\u003e\u003cbreak time=\"10ms\"/\u003e\u003c/speak\u003e" ]
      } ],
      "currentFlow": {
        "name": "ZExit"
      },
      "actions": [ {
        "userUtterance": {
          "text": "no"
        }
      }, {
        "agentUtterance": {
          "text": "\u003cspeak\u003eThank you for contacting Uber Phone Support.\u003c/speak\u003e\n\u003cspeak\u003e\u003cbreak time=\"10ms\"/\u003e\u003c/speak\u003e"
        }
      } ]
    }
  } ],
  "creationTime": {
    "seconds": 1704444741,
    "nanos": 125400000
  },
  "testConfig": {
    "flow": "Default Start Flow",
    "page": "Start Page"
  },
  "languageCode": "en"
}
